{"id": "JvDnmTdjg7E", "title": "[Official Audio] \ucc38\uae68\uc640 \uc19c\uc0ac\ud0d5(Chamsom) - \uc774\uc990\uaed8(Forget you)", "formats": [{"asr": 48000, "filesize": 1397378, "format_id": "249", "format_note": "tiny", "fps": null, "height": null, "quality": 0, "tbr": 55.335, "url": "https://r5---sn-a5msen7z.googlevideo.com/videoplayback?expire=1639283806&ei=_ie1YYENgrK7Aq-ls6AM&ip=66.214.92.208&id=o-ANL3vidtLiUQAAqrSW1Dtde0iaKhMlbpSAQnAyhv6V5m&itag=249&source=youtube&requiressl=yes&mh=AH&mm=31%2C29&mn=sn-a5msen7z%2Csn-a5meknzs&ms=au%2Crdu&mv=m&mvi=5&pl=20&ctier=A&pfa=5&initcwndbps=2172500&hightc=yes&vprv=1&mime=audio%2Fwebm&ns=t2F5qZ-d7t3LU6Cz0gIBCo4G&gir=yes&clen=1397378&dur=202.021&lmt=1541908702194717&mt=1639261729&fvip=5&keepalive=yes&fexp=24001373%2C24007246&c=WEB&txp=5411222&n=YUPjBKJQ2Sav8E&sparams=expire%2Cei%2Cip%2Cid%2Citag%2Csource%2Crequiressl%2Cctier%2Cpfa%2Chightc%2Cvprv%2Cmime%2Cns%2Cgir%2Cclen%2Cdur%2Clmt&lsparams=mh%2Cmm%2Cmn%2Cms%2Cmv%2Cmvi%2Cpl%2Cinitcwndbps&lsig=AG3C_xAwRQIgYuqVnkCq-spCElXkaeTuAjNLuC8VT37cKHLSu2r31UACIQCkInxEtGA-sViGloSh6VT_vombVP1ii2RSfFpVJ_qv2Q%3D%3D&sig=AOq0QJ8wRQIgI2QE5wjrv3PUgLskIWNrJt4diwvzYBlpyw1l-Wnmk-0CIQCG0-Wp9a5VURL3pYEOLtuWcnZYOZHF-p5y4qlARqDTAA==", "width": null, "ext": "webm", "vcodec": "none", "acodec": "opus", "abr": 55.335, "downloader_options": {"http_chunk_size": 10485760}, "container": "webm_dash", "format": "249 - audio only (tiny)", "protocol": "https", "http_headers": {"User-Agent": "Mozilla/5.0 (Windows NT 10.0; Win64; x64) AppleWebKit/537.36 (KHTML, like Gecko) Chrome/71.0.3578.1 Safari/537.36", "Accept-Charset": "ISO-8859-1,utf-8;q=0.7,*;q=0.7", "Accept": "text/html,application/xhtml+xml,application/xml;q=0.9,*/*;q=0.8", "Accept-Encoding": "gzip, deflate", "Accept-Language": "en-us,en;q=0.5"}}, {"asr": 48000, "filesize": 1810377, "format_id": "250", "format_note": "tiny", "fps": null, "height": null, "quality": 0, "tbr": 71.69, "url": "https://r5---sn-a5msen7z.googlevideo.com/videoplayback?expire=1639283806&ei=_ie1YYENgrK7Aq-ls6AM&ip=66.214.92.208&id=o-ANL3vidtLiUQAAqrSW1Dtde0iaKhMlbpSAQnAyhv6V5m&itag=250&source=youtube&requiressl=yes&mh=AH&mm=31%2C29&mn=sn-a5msen7z%2Csn-a5meknzs&ms=au%2Crdu&mv=m&mvi=5&pl=20&ctier=A&pfa=5&initcwndbps=2172500&hightc=yes&vprv=1&mime=audio%2Fwebm&ns=t2F5qZ-d7t3LU6Cz0gIBCo4G&gir=yes&clen=1810377&dur=202.021&lmt=1541908700479781&mt=1639261729&fvip=5&keepalive=yes&fexp=24001373%2C24007246&c=WEB&txp=5411222&n=YUPjBKJQ2Sav8E&sparams=expire%2Cei%2Cip%2Cid%2Citag%2Csource%2Crequiressl%2Cctier%2Cpfa%2Chightc%2Cvprv%2Cmime%2Cns%2Cgir%2Cclen%2Cdur%2Clmt&lsparams=mh%2Cmm%2Cmn%2Cms%2Cmv%2Cmvi%2Cpl%2Cinitcwndbps&lsig=AG3C_xAwRAIgCSNdK9lxEaCWvWlNNFvr-_k2iSU52bcjA42CwmyM0wkCIHiC4AbqX20qh8CO7ZewRH912p-fivNh5I3nxaZofVKZ&sig=AOq0QJ8wRQIhAIEQHnEcccBlXwlx4IRkvEK5PM7T1-NhenD4v3aQckpOAiAOK-vSDMdrAtGeF2Y_RC7e-A6aHU6HARiC2N_uaik2XA==", "width": null, "ext": "webm", "vcodec": "none", "acodec": "opus", "abr": 71.69, "downloader_options": {"http_chunk_size": 10485760}, "container": "webm_dash", "format": "250 - audio only (tiny)", "protocol": "https", "http_headers": {"User-Agent": "Mozilla/5.0 (Windows NT 10.0; Win64; x64) AppleWebKit/537.36 (KHTML, like Gecko) Chrome/71.0.3578.1 Safari/537.36", "Accept-Charset": "ISO-8859-1,utf-8;q=0.7,*;q=0.7", "Accept": "text/html,application/xhtml+xml,application/xml;q=0.9,*/*;q=0.8", "Accept-Encoding": "gzip, deflate", "Accept-Language": "en-us,en;q=0.5"}}, {"asr": 44100, "filesize": 3209974, "format_id": "140", "format_note": "tiny", "fps": null, "height": null, "quality": 0, "tbr": 127.089, "url": "https://r5---sn-a5msen7z.googlevideo.com/videoplayback?expire=1639283806&ei=_ie1YYENgrK7Aq-ls6AM&ip=66.214.92.208&id=o-ANL3vidtLiUQAAqrSW1Dtde0iaKhMlbpSAQnAyhv6V5m&itag=140&source=youtube&requiressl=yes&mh=AH&mm=31%2C29&mn=sn-a5msen7z%2Csn-a5meknzs&ms=au%2Crdu&mv=m&mvi=5&pl=20&ctier=A&pfa=5&initcwndbps=2172500&hightc=yes&vprv=1&mime=audio%2Fmp4&ns=t2F5qZ-d7t3LU6Cz0gIBCo4G&gir=yes&clen=3209974&dur=202.060&lmt=1541906661488950&mt=1639261729&fvip=5&keepalive=yes&fexp=24001373%2C24007246&c=WEB&txp=5432432&n=YUPjBKJQ2Sav8E&sparams=expire%2Cei%2Cip%2Cid%2Citag%2Csource%2Crequiressl%2Cctier%2Cpfa%2Chightc%2Cvprv%2Cmime%2Cns%2Cgir%2Cclen%2Cdur%2Clmt&lsparams=mh%2Cmm%2Cmn%2Cms%2Cmv%2Cmvi%2Cpl%2Cinitcwndbps&lsig=AG3C_xAwRgIhAMU72OYyT5v1ObI5uCExLN9dJaV4K3YMOpCJHGTwyttkAiEA7r1Wu--xtP7EtfXEKGuK1cPR_qQIpdyC96KDfuohEtg%3D&sig=AOq0QJ8wRQIhAP9-gwXs75WSZbZCcv9B2F8Pq-k0QfW2ApFRhnjNbUn5AiA1uh4KoiwD7-GctjYbNPMEnGdH2kvx7EHSIdUrddtwZw==", "width": null, "ext": "m4a", "vcodec": "none", "acodec": "mp4a.40.2", "abr": 127.089, "downloader_options": {"http_chunk_size": 10485760}, "container": "m4a_dash", "format": "140 - audio only (tiny)", "protocol": "https", "http_headers": {"User-Agent": "Mozilla/5.0 (Windows NT 10.0; Win64; x64) AppleWebKit/537.36 (KHTML, like Gecko) Chrome/71.0.3578.1 Safari/537.36", "Accept-Charset": "ISO-8859-1,utf-8;q=0.7,*;q=0.7", "Accept": "text/html,application/xhtml+xml,application/xml;q=0.9,*/*;q=0.8", "Accept-Encoding": "gzip, deflate", "Accept-Language": "en-us,en;q=0.5"}}, {"asr": 48000, "filesize": 3521825, "format_id": "251", "format_note": "tiny", "fps": null, "height": null, "quality": 0, "tbr": 139.463, "url": "https://r5---sn-a5msen7z.googlevideo.com/videoplayback?expire=1639283806&ei=_ie1YYENgrK7Aq-ls6AM&ip=66.214.92.208&id=o-ANL3vidtLiUQAAqrSW1Dtde0iaKhMlbpSAQnAyhv6V5m&itag=251&source=youtube&requiressl=yes&mh=AH&mm=31%2C29&mn=sn-a5msen7z%2Csn-a5meknzs&ms=au%2Crdu&mv=m&mvi=5&pl=20&ctier=A&pfa=5&initcwndbps=2172500&hightc=yes&vprv=1&mime=audio%2Fwebm&ns=t2F5qZ-d7t3LU6Cz0gIBCo4G&gir=yes&clen=3521825&dur=202.021&lmt=1541908700464693&mt=1639261729&fvip=5&keepalive=yes&fexp=24001373%2C24007246&c=WEB&txp=5411222&n=YUPjBKJQ2Sav8E&sparams=expire%2Cei%2Cip%2Cid%2Citag%2Csource%2Crequiressl%2Cctier%2Cpfa%2Chightc%2Cvprv%2Cmime%2Cns%2Cgir%2Cclen%2Cdur%2Clmt&lsparams=mh%2Cmm%2Cmn%2Cms%2Cmv%2Cmvi%2Cpl%2Cinitcwndbps&lsig=AG3C_xAwRgIhAMKjd2EivLozmwGerkEtoALsKD1H2XiN7QeMcAN06kRiAiEA9BKD6EI7IF85yT2xas6vsIarL0kHFJxe7y6LNv1GaOw%3D&sig=AOq0QJ8wRAIgackX4vfGqorUNIN726BEdqS2AN5sxAWnRD5UmEiPeocCIDZ2sCGfI21niXseQHvn7uzyrB7Jod1vfeelXXQU4VZl", "width": null, "ext": "webm", "vcodec": "none", "acodec": "opus", "abr": 139.463, "downloader_options": {"http_chunk_size": 10485760}, "container": "webm_dash", "format": "251 - audio only (tiny)", "protocol": "https", "http_headers": {"User-Agent": "Mozilla/5.0 (Windows NT 10.0; Win64; x64) AppleWebKit/537.36 (KHTML, like Gecko) Chrome/71.0.3578.1 Safari/537.36", "Accept-Charset": "ISO-8859-1,utf-8;q=0.7,*;q=0.7", "Accept": "text/html,application/xhtml+xml,application/xml;q=0.9,*/*;q=0.8", "Accept-Encoding": "gzip, deflate", "Accept-Language": "en-us,en;q=0.5"}}, {"asr": null, "filesize": 298740, "format_id": "160", "format_note": "144p", "fps": 30, "height": 144, "quality": 0, "tbr": 11.833, "url": "https://r5---sn-a5msen7z.googlevideo.com/videoplayback?expire=1639283806&ei=_ie1YYENgrK7Aq-ls6AM&ip=66.214.92.208&id=o-ANL3vidtLiUQAAqrSW1Dtde0iaKhMlbpSAQnAyhv6V5m&itag=160&aitags=133%2C134%2C135%2C136%2C137%2C160%2C242%2C243%2C244%2C247%2C248%2C278&source=youtube&requiressl=yes&mh=AH&mm=31%2C29&mn=sn-a5msen7z%2Csn-a5meknzs&ms=au%2Crdu&mv=m&mvi=5&pl=20&ctier=A&pfa=5&initcwndbps=2172500&hightc=yes&vprv=1&mime=video%2Fmp4&ns=t2F5qZ-d7t3LU6Cz0gIBCo4G&gir=yes&clen=298740&dur=201.968&lmt=1541906831582201&mt=1639261729&fvip=5&keepalive=yes&fexp=24001373%2C24007246&c=WEB&txp=5432432&n=YUPjBKJQ2Sav8E&sparams=expire%2Cei%2Cip%2Cid%2Caitags%2Csource%2Crequiressl%2Cctier%2Cpfa%2Chightc%2Cvprv%2Cmime%2Cns%2Cgir%2Cclen%2Cdur%2Clmt&lsparams=mh%2Cmm%2Cmn%2Cms%2Cmv%2Cmvi%2Cpl%2Cinitcwndbps&lsig=AG3C_xAwRQIhAKKIHrpp_iDsiGPdgngoSS5AjbK9Nsy7qWFRZnVxu-gBAiAd7dOmnbQt5F8a1Od73HDU3DYdo-lrQnvWzrVBbiHYOA%3D%3D&sig=AOq0QJ8wRAIgRiSx76sAcxwem1XMz8ZgIyPM9J46yQm1lQxQgrqQ23ICIGU7KDv0N6paHiQROQChW_c5HfhEQsHmTM_IC9lhoeZ8", "width": 256, "ext": "mp4", "vcodec": "avc1.4d400c", "acodec": "none", "vbr": 11.833, "downloader_options": {"http_chunk_size": 10485760}, "container": "mp4_dash", "format": "160 - 256x144 (144p)", "protocol": "https", "http_headers": {"User-Agent": "Mozilla/5.0 (Windows NT 10.0; Win64; x64) AppleWebKit/537.36 (KHTML, like Gecko) Chrome/71.0.3578.1 Safari/537.36", "Accept-Charset": "ISO-8859-1,utf-8;q=0.7,*;q=0.7", "Accept": "text/html,application/xhtml+xml,application/xml;q=0.9,*/*;q=0.8", "Accept-Encoding": "gzip, deflate", "Accept-Language": "en-us,en;q=0.5"}}, {"asr": null, "filesize": 367769, "format_id": "278", "format_note": "144p", "fps": 30, "height": 144, "quality": 0, "tbr": 14.567, "url": "https://r5---sn-a5msen7z.googlevideo.com/videoplayback?expire=1639283806&ei=_ie1YYENgrK7Aq-ls6AM&ip=66.214.92.208&id=o-ANL3vidtLiUQAAqrSW1Dtde0iaKhMlbpSAQnAyhv6V5m&itag=278&aitags=133%2C134%2C135%2C136%2C137%2C160%2C242%2C243%2C244%2C247%2C248%2C278&source=youtube&requiressl=yes&mh=AH&mm=31%2C29&mn=sn-a5msen7z%2Csn-a5meknzs&ms=au%2Crdu&mv=m&mvi=5&pl=20&ctier=A&pfa=5&initcwndbps=2172500&hightc=yes&vprv=1&mime=video%2Fwebm&ns=t2F5qZ-d7t3LU6Cz0gIBCo4G&gir=yes&clen=367769&dur=201.968&lmt=1541907888541500&mt=1639261729&fvip=5&keepalive=yes&fexp=24001373%2C24007246&c=WEB&txp=5432432&n=YUPjBKJQ2Sav8E&sparams=expire%2Cei%2Cip%2Cid%2Caitags%2Csource%2Crequiressl%2Cctier%2Cpfa%2Chightc%2Cvprv%2Cmime%2Cns%2Cgir%2Cclen%2Cdur%2Clmt&lsparams=mh%2Cmm%2Cmn%2Cms%2Cmv%2Cmvi%2Cpl%2Cinitcwndbps&lsig=AG3C_xAwRQIgNo_gpL6vfnxIfE5L_xbdnNMXiVbIgG-L8XQhrxhVzAUCIQCLdi4rUJAfHT_tmtMT1QgRsLsRHT5KRwTB26pM4XQVTA%3D%3D&sig=AOq0QJ8wRQIhAJs28Hb7Ih16gF8yGbnmoaVCw4qEl5DUpLOYPmMSbgmaAiBbV-Vi7XQk7TdC7HjjRa-JjlxyFjDy97AjU2L4vwv67w==", "width": 256, "ext": "webm", "vcodec": "vp9", "acodec": "none", "vbr": 14.567, "downloader_options": {"http_chunk_size": 10485760}, "container": "webm_dash", "format": "278 - 256x144 (144p)", "protocol": "https", "http_headers": {"User-Agent": "Mozilla/5.0 (Windows NT 10.0; Win64; x64) AppleWebKit/537.36 (KHTML, like Gecko) Chrome/71.0.3578.1 Safari/537.36", "Accept-Charset": "ISO-8859-1,utf-8;q=0.7,*;q=0.7", "Accept": "text/html,application/xhtml+xml,application/xml;q=0.9,*/*;q=0.8", "Accept-Encoding": "gzip, deflate", "Accept-Language": "en-us,en;q=0.5"}}, {"asr": null, "filesize": 333071, "format_id": "133", "format_note": "240p", "fps": 30, "height": 240, "quality": 1, "tbr": 13.193, "url": "https://r5---sn-a5msen7z.googlevideo.com/videoplayback?expire=1639283806&ei=_ie1YYENgrK7Aq-ls6AM&ip=66.214.92.208&id=o-ANL3vidtLiUQAAqrSW1Dtde0iaKhMlbpSAQnAyhv6V5m&itag=133&aitags=133%2C134%2C135%2C136%2C137%2C160%2C242%2C243%2C244%2C247%2C248%2C278&source=youtube&requiressl=yes&mh=AH&mm=31%2C29&mn=sn-a5msen7z%2Csn-a5meknzs&ms=au%2Crdu&mv=m&mvi=5&pl=20&ctier=A&pfa=5&initcwndbps=2172500&hightc=yes&vprv=1&mime=video%2Fmp4&ns=t2F5qZ-d7t3LU6Cz0gIBCo4G&gir=yes&clen=333071&dur=201.968&lmt=1541906812508010&mt=1639261729&fvip=5&keepalive=yes&fexp=24001373%2C24007246&c=WEB&txp=5432432&n=YUPjBKJQ2Sav8E&sparams=expire%2Cei%2Cip%2Cid%2Caitags%2Csource%2Crequiressl%2Cctier%2Cpfa%2Chightc%2Cvprv%2Cmime%2Cns%2Cgir%2Cclen%2Cdur%2Clmt&lsparams=mh%2Cmm%2Cmn%2Cms%2Cmv%2Cmvi%2Cpl%2Cinitcwndbps&lsig=AG3C_xAwRQIhALlL3tFYRH9CF5o40CWuIyWwTkMWGyhdmmZuuf_suicsAiB58raUKt23ohL6VlFrEEAKFVyREw-UhqFAP7p0ARjtJA%3D%3D&sig=AOq0QJ8wRgIhAOAf7hAbRQuhU3o9_k3QBGODAIZhmopI_VQPowSVJGMPAiEAkvgJ-KsXJX5hoNcbww9TdY5oCtW1XohV-4p7MQY6IYM=", "width": 426, "ext": "mp4", "vcodec": "avc1.4d4015", "acodec": "none", "vbr": 13.193, "downloader_options": {"http_chunk_size": 10485760}, "container": "mp4_dash", "format": "133 - 426x240 (240p)", "protocol": "https", "http_headers": {"User-Agent": "Mozilla/5.0 (Windows NT 10.0; Win64; x64) AppleWebKit/537.36 (KHTML, like Gecko) Chrome/71.0.3578.1 Safari/537.36", "Accept-Charset": "ISO-8859-1,utf-8;q=0.7,*;q=0.7", "Accept": "text/html,application/xhtml+xml,application/xml;q=0.9,*/*;q=0.8", "Accept-Encoding": "gzip, deflate", "Accept-Language": "en-us,en;q=0.5"}}, {"asr": null, "filesize": 477191, "format_id": "242", "format_note": "240p", "fps": 30, "height": 240, "quality": 1, "tbr": 18.901, "url": "https://r5---sn-a5msen7z.googlevideo.com/videoplayback?expire=1639283806&ei=_ie1YYENgrK7Aq-ls6AM&ip=66.214.92.208&id=o-ANL3vidtLiUQAAqrSW1Dtde0iaKhMlbpSAQnAyhv6V5m&itag=242&aitags=133%2C134%2C135%2C136%2C137%2C160%2C242%2C243%2C244%2C247%2C248%2C278&source=youtube&requiressl=yes&mh=AH&mm=31%2C29&mn=sn-a5msen7z%2Csn-a5meknzs&ms=au%2Crdu&mv=m&mvi=5&pl=20&ctier=A&pfa=5&initcwndbps=2172500&hightc=yes&vprv=1&mime=video%2Fwebm&ns=t2F5qZ-d7t3LU6Cz0gIBCo4G&gir=yes&clen=477191&dur=201.968&lmt=1541907888540496&mt=1639261729&fvip=5&keepalive=yes&fexp=24001373%2C24007246&c=WEB&txp=5432432&n=YUPjBKJQ2Sav8E&sparams=expire%2Cei%2Cip%2Cid%2Caitags%2Csource%2Crequiressl%2Cctier%2Cpfa%2Chightc%2Cvprv%2Cmime%2Cns%2Cgir%2Cclen%2Cdur%2Clmt&lsparams=mh%2Cmm%2Cmn%2Cms%2Cmv%2Cmvi%2Cpl%2Cinitcwndbps&lsig=AG3C_xAwRAIgeNrPVo4RoolpPiVl8cVDRlZexl1lXi0lFhu7yvWX8sICIGglOQeX-1MlMwau91HsPDFW2nbLEvVdnxOJLikYmUkC&sig=AOq0QJ8wRAIgcvbE5XhnU8CzS03p_l79NCQPrIJoJW5n1wigy5Wnc24CIGqyBFiiKo7BxH6XeUcbMdiyy6YbyJjaDYL55mDvRyx1", "width": 426, "ext": "webm", "vcodec": "vp9", "acodec": "none", "vbr": 18.901, "downloader_options": {"http_chunk_size": 10485760}, "container": "webm_dash", "format": "242 - 426x240 (240p)", "protocol": "https", "http_headers": {"User-Agent": "Mozilla/5.0 (Windows NT 10.0; Win64; x64) AppleWebKit/537.36 (KHTML, like Gecko) Chrome/71.0.3578.1 Safari/537.36", "Accept-Charset": "ISO-8859-1,utf-8;q=0.7,*;q=0.7", "Accept": "text/html,application/xhtml+xml,application/xml;q=0.9,*/*;q=0.8", "Accept-Encoding": "gzip, deflate", "Accept-Language": "en-us,en;q=0.5"}}, {"asr": null, "filesize": 412695, "format_id": "134", "format_note": "360p", "fps": 30, "height": 360, "quality": 2, "tbr": 16.346, "url": "https://r5---sn-a5msen7z.googlevideo.com/videoplayback?expire=1639283806&ei=_ie1YYENgrK7Aq-ls6AM&ip=66.214.92.208&id=o-ANL3vidtLiUQAAqrSW1Dtde0iaKhMlbpSAQnAyhv6V5m&itag=134&aitags=133%2C134%2C135%2C136%2C137%2C160%2C242%2C243%2C244%2C247%2C248%2C278&source=youtube&requiressl=yes&mh=AH&mm=31%2C29&mn=sn-a5msen7z%2Csn-a5meknzs&ms=au%2Crdu&mv=m&mvi=5&pl=20&ctier=A&pfa=5&initcwndbps=2172500&hightc=yes&vprv=1&mime=video%2Fmp4&ns=t2F5qZ-d7t3LU6Cz0gIBCo4G&gir=yes&clen=412695&dur=201.968&lmt=1541906747970697&mt=1639261729&fvip=5&keepalive=yes&fexp=24001373%2C24007246&c=WEB&txp=5432432&n=YUPjBKJQ2Sav8E&sparams=expire%2Cei%2Cip%2Cid%2Caitags%2Csource%2Crequiressl%2Cctier%2Cpfa%2Chightc%2Cvprv%2Cmime%2Cns%2Cgir%2Cclen%2Cdur%2Clmt&lsparams=mh%2Cmm%2Cmn%2Cms%2Cmv%2Cmvi%2Cpl%2Cinitcwndbps&lsig=AG3C_xAwRAIgcEtiiGumEL7q5xnNtxodQFl7l7ezkOO5k0kLnbBMVR4CIAJY4c82YTeXW374Hv-hQ4SOTIZ4IH0dRTJlbv9n_7nT&sig=AOq0QJ8wRgIhAOPg6tRl_pORBaB_6GfuxSjS5VAVfuThZYyrvSYjb4IxAiEAuWBzx34sTIzbpO08MXp_1nhm4cx8doA4CsMq8_buzAs=", "width": 640, "ext": "mp4", "vcodec": "avc1.4d401e", "acodec": "none", "vbr": 16.346, "downloader_options": {"http_chunk_size": 10485760}, "container": "mp4_dash", "format": "134 - 640x360 (360p)", "protocol": "https", "http_headers": {"User-Agent": "Mozilla/5.0 (Windows NT 10.0; Win64; x64) AppleWebKit/537.36 (KHTML, like Gecko) Chrome/71.0.3578.1 Safari/537.36", "Accept-Charset": "ISO-8859-1,utf-8;q=0.7,*;q=0.7", "Accept": "text/html,application/xhtml+xml,application/xml;q=0.9,*/*;q=0.8", "Accept-Encoding": "gzip, deflate", "Accept-Language": "en-us,en;q=0.5"}}, {"asr": null, "filesize": 809093, "format_id": "243", "format_note": "360p", "fps": 30, "height": 360, "quality": 2, "tbr": 32.048, "url": "https://r5---sn-a5msen7z.googlevideo.com/videoplayback?expire=1639283806&ei=_ie1YYENgrK7Aq-ls6AM&ip=66.214.92.208&id=o-ANL3vidtLiUQAAqrSW1Dtde0iaKhMlbpSAQnAyhv6V5m&itag=243&aitags=133%2C134%2C135%2C136%2C137%2C160%2C242%2C243%2C244%2C247%2C248%2C278&source=youtube&requiressl=yes&mh=AH&mm=31%2C29&mn=sn-a5msen7z%2Csn-a5meknzs&ms=au%2Crdu&mv=m&mvi=5&pl=20&ctier=A&pfa=5&initcwndbps=2172500&hightc=yes&vprv=1&mime=video%2Fwebm&ns=t2F5qZ-d7t3LU6Cz0gIBCo4G&gir=yes&clen=809093&dur=201.968&lmt=1541907888553904&mt=1639261729&fvip=5&keepalive=yes&fexp=24001373%2C24007246&c=WEB&txp=5432432&n=YUPjBKJQ2Sav8E&sparams=expire%2Cei%2Cip%2Cid%2Caitags%2Csource%2Crequiressl%2Cctier%2Cpfa%2Chightc%2Cvprv%2Cmime%2Cns%2Cgir%2Cclen%2Cdur%2Clmt&lsparams=mh%2Cmm%2Cmn%2Cms%2Cmv%2Cmvi%2Cpl%2Cinitcwndbps&lsig=AG3C_xAwRQIhAN53yKC2y9Tcq2LKPbvtiSak4LEqGQuyC4ST0sr4hFPyAiBG_tV-8tXNjN3_Dck484_yw45V41hyn69js-PTUsqwcw%3D%3D&sig=AOq0QJ8wRQIgRvyMOlfN7djYc3QO-pfTIm0hgpZ2pVoPHC5ik6v58isCIQCmBJCI1YpFJBfzQmvsFA6f5ltZay_WtPGm5ARfFEuwWg==", "width": 640, "ext": "webm", "vcodec": "vp9", "acodec": "none", "vbr": 32.048, "downloader_options": {"http_chunk_size": 10485760}, "container": "webm_dash", "format": "243 - 640x360 (360p)", "protocol": "https", "http_headers": {"User-Agent": "Mozilla/5.0 (Windows NT 10.0; Win64; x64) AppleWebKit/537.36 (KHTML, like Gecko) Chrome/71.0.3578.1 Safari/537.36", "Accept-Charset": "ISO-8859-1,utf-8;q=0.7,*;q=0.7", "Accept": "text/html,application/xhtml+xml,application/xml;q=0.9,*/*;q=0.8", "Accept-Encoding": "gzip, deflate", "Accept-Language": "en-us,en;q=0.5"}}, {"asr": null, "filesize": 662787, "format_id": "135", "format_note": "480p", "fps": 30, "height": 480, "quality": 3, "tbr": 26.253, "url": "https://r5---sn-a5msen7z.googlevideo.com/videoplayback?expire=1639283806&ei=_ie1YYENgrK7Aq-ls6AM&ip=66.214.92.208&id=o-ANL3vidtLiUQAAqrSW1Dtde0iaKhMlbpSAQnAyhv6V5m&itag=135&aitags=133%2C134%2C135%2C136%2C137%2C160%2C242%2C243%2C244%2C247%2C248%2C278&source=youtube&requiressl=yes&mh=AH&mm=31%2C29&mn=sn-a5msen7z%2Csn-a5meknzs&ms=au%2Crdu&mv=m&mvi=5&pl=20&ctier=A&pfa=5&initcwndbps=2172500&hightc=yes&vprv=1&mime=video%2Fmp4&ns=t2F5qZ-d7t3LU6Cz0gIBCo4G&gir=yes&clen=662787&dur=201.968&lmt=1541906748174203&mt=1639261729&fvip=5&keepalive=yes&fexp=24001373%2C24007246&c=WEB&txp=5432432&n=YUPjBKJQ2Sav8E&sparams=expire%2Cei%2Cip%2Cid%2Caitags%2Csource%2Crequiressl%2Cctier%2Cpfa%2Chightc%2Cvprv%2Cmime%2Cns%2Cgir%2Cclen%2Cdur%2Clmt&lsparams=mh%2Cmm%2Cmn%2Cms%2Cmv%2Cmvi%2Cpl%2Cinitcwndbps&lsig=AG3C_xAwRQIga7PoeUckHbNuTJMFfrSX-bKaDAp2pCVz7tT5FAy4DhkCIQC1xOWwUK1dY4022pxTSIiInm1G22aXp0tyyueZla-LbQ%3D%3D&sig=AOq0QJ8wRQIgGS5XzAIYnHVKhzpLlODJWjmRyLw-nnBzJkXd3nHiF6ECIQCPy-hwwonOwu-Epa1RfpbTA_B-TA7-w3bVTkgqlCSh-A==", "width": 854, "ext": "mp4", "vcodec": "avc1.4d401f", "acodec": "none", "vbr": 26.253, "downloader_options": {"http_chunk_size": 10485760}, "container": "mp4_dash", "format": "135 - 854x480 (480p)", "protocol": "https", "http_headers": {"User-Agent": "Mozilla/5.0 (Windows NT 10.0; Win64; x64) AppleWebKit/537.36 (KHTML, like Gecko) Chrome/71.0.3578.1 Safari/537.36", "Accept-Charset": "ISO-8859-1,utf-8;q=0.7,*;q=0.7", "Accept": "text/html,application/xhtml+xml,application/xml;q=0.9,*/*;q=0.8", "Accept-Encoding": "gzip, deflate", "Accept-Language": "en-us,en;q=0.5"}}, {"asr": null, "filesize": 779312, "format_id": "244", "format_note": "480p", "fps": 30, "height": 480, "quality": 3, "tbr": 30.868, "url": "https://r5---sn-a5msen7z.googlevideo.com/videoplayback?expire=1639283806&ei=_ie1YYENgrK7Aq-ls6AM&ip=66.214.92.208&id=o-ANL3vidtLiUQAAqrSW1Dtde0iaKhMlbpSAQnAyhv6V5m&itag=244&aitags=133%2C134%2C135%2C136%2C137%2C160%2C242%2C243%2C244%2C247%2C248%2C278&source=youtube&requiressl=yes&mh=AH&mm=31%2C29&mn=sn-a5msen7z%2Csn-a5meknzs&ms=au%2Crdu&mv=m&mvi=5&pl=20&ctier=A&pfa=5&initcwndbps=2172500&hightc=yes&vprv=1&mime=video%2Fwebm&ns=t2F5qZ-d7t3LU6Cz0gIBCo4G&gir=yes&clen=779312&dur=201.968&lmt=1541907888548193&mt=1639261729&fvip=5&keepalive=yes&fexp=24001373%2C24007246&c=WEB&txp=5432432&n=YUPjBKJQ2Sav8E&sparams=expire%2Cei%2Cip%2Cid%2Caitags%2Csource%2Crequiressl%2Cctier%2Cpfa%2Chightc%2Cvprv%2Cmime%2Cns%2Cgir%2Cclen%2Cdur%2Clmt&lsparams=mh%2Cmm%2Cmn%2Cms%2Cmv%2Cmvi%2Cpl%2Cinitcwndbps&lsig=AG3C_xAwRQIhAP7RxrnJMnoH3H_cBRo4uDpXPwYEQo0F0cFUrVTshXBZAiAXLnsALH3n4IHe14d0yxqHSbtw457aEk012ly0ua3I5g%3D%3D&sig=AOq0QJ8wRgIhAJfSol7jeK5QyHstfV0OXfAn7yDI4yXj_L8qkE8ViVy7AiEA_Zig5u2PaSQicDbpjyoKxenqnG0XTwGgUaoptjoYDu4=", "width": 854, "ext": "webm", "vcodec": "vp9", "acodec": "none", "vbr": 30.868, "downloader_options": {"http_chunk_size": 10485760}, "container": "webm_dash", "format": "244 - 854x480 (480p)", "protocol": "https", "http_headers": {"User-Agent": "Mozilla/5.0 (Windows NT 10.0; Win64; x64) AppleWebKit/537.36 (KHTML, like Gecko) Chrome/71.0.3578.1 Safari/537.36", "Accept-Charset": "ISO-8859-1,utf-8;q=0.7,*;q=0.7", "Accept": "text/html,application/xhtml+xml,application/xml;q=0.9,*/*;q=0.8", "Accept-Encoding": "gzip, deflate", "Accept-Language": "en-us,en;q=0.5"}}, {"asr": null, "filesize": 1022472, "format_id": "136", "format_note": "720p", "fps": 30, "height": 720, "quality": 4, "tbr": 40.5, "url": "https://r5---sn-a5msen7z.googlevideo.com/videoplayback?expire=1639283806&ei=_ie1YYENgrK7Aq-ls6AM&ip=66.214.92.208&id=o-ANL3vidtLiUQAAqrSW1Dtde0iaKhMlbpSAQnAyhv6V5m&itag=136&aitags=133%2C134%2C135%2C136%2C137%2C160%2C242%2C243%2C244%2C247%2C248%2C278&source=youtube&requiressl=yes&mh=AH&mm=31%2C29&mn=sn-a5msen7z%2Csn-a5meknzs&ms=au%2Crdu&mv=m&mvi=5&pl=20&ctier=A&pfa=5&initcwndbps=2172500&hightc=yes&vprv=1&mime=video%2Fmp4&ns=t2F5qZ-d7t3LU6Cz0gIBCo4G&gir=yes&clen=1022472&dur=201.968&lmt=1541906813910979&mt=1639261729&fvip=5&keepalive=yes&fexp=24001373%2C24007246&c=WEB&txp=5432432&n=YUPjBKJQ2Sav8E&sparams=expire%2Cei%2Cip%2Cid%2Caitags%2Csource%2Crequiressl%2Cctier%2Cpfa%2Chightc%2Cvprv%2Cmime%2Cns%2Cgir%2Cclen%2Cdur%2Clmt&lsparams=mh%2Cmm%2Cmn%2Cms%2Cmv%2Cmvi%2Cpl%2Cinitcwndbps&lsig=AG3C_xAwRgIhAII7tuCCuP5zszweqXFoDcdB3cDu4_A99ZtHfwroP3ZmAiEAqe1h6cspp2YhBi0OamAG3LL504TsbUg65VwGu1utKis%3D&sig=AOq0QJ8wRQIgRYwSiiGa7HKxSpEBUMZAKp0LG0Xmc8GaVmJEN9w1SDACIQDbH36qp5149aPt-XkUZ8JioykIAymE62K3Vx2Uc8Ozaw==", "width": 1280, "ext": "mp4", "vcodec": "avc1.4d401f", "acodec": "none", "vbr": 40.5, "downloader_options": {"http_chunk_size": 10485760}, "container": "mp4_dash", "format": "136 - 1280x720 (720p)", "protocol": "https", "http_headers": {"User-Agent": "Mozilla/5.0 (Windows NT 10.0; Win64; x64) AppleWebKit/537.36 (KHTML, like Gecko) Chrome/71.0.3578.1 Safari/537.36", "Accept-Charset": "ISO-8859-1,utf-8;q=0.7,*;q=0.7", "Accept": "text/html,application/xhtml+xml,application/xml;q=0.9,*/*;q=0.8", "Accept-Encoding": "gzip, deflate", "Accept-Language": "en-us,en;q=0.5"}}, {"asr": null, "filesize": 2164388, "format_id": "247", "format_note": "720p", "fps": 30, "height": 720, "quality": 4, "tbr": 85.731, "url": "https://r5---sn-a5msen7z.googlevideo.com/videoplayback?expire=1639283806&ei=_ie1YYENgrK7Aq-ls6AM&ip=66.214.92.208&id=o-ANL3vidtLiUQAAqrSW1Dtde0iaKhMlbpSAQnAyhv6V5m&itag=247&aitags=133%2C134%2C135%2C136%2C137%2C160%2C242%2C243%2C244%2C247%2C248%2C278&source=youtube&requiressl=yes&mh=AH&mm=31%2C29&mn=sn-a5msen7z%2Csn-a5meknzs&ms=au%2Crdu&mv=m&mvi=5&pl=20&ctier=A&pfa=5&initcwndbps=2172500&hightc=yes&vprv=1&mime=video%2Fwebm&ns=t2F5qZ-d7t3LU6Cz0gIBCo4G&gir=yes&clen=2164388&dur=201.968&lmt=1541907888559866&mt=1639261729&fvip=5&keepalive=yes&fexp=24001373%2C24007246&c=WEB&txp=5432432&n=YUPjBKJQ2Sav8E&sparams=expire%2Cei%2Cip%2Cid%2Caitags%2Csource%2Crequiressl%2Cctier%2Cpfa%2Chightc%2Cvprv%2Cmime%2Cns%2Cgir%2Cclen%2Cdur%2Clmt&lsparams=mh%2Cmm%2Cmn%2Cms%2Cmv%2Cmvi%2Cpl%2Cinitcwndbps&lsig=AG3C_xAwRgIhAL_TmpHw0kNyQtBToJMCVMkesgSh_w2G7vFIQ7-ic-LNAiEAlOSWJE4RDqfYGDb6Z1iYO_1bEVU5TotPJqpdzn0J5nE%3D&sig=AOq0QJ8wRQIhAOM5Q3WANl262cHfozI7vCRbUAcxslrJeDFtVSLv8-BZAiB2hqbQmNqSW1q2bh1nwJB2WwUco4zGwAkn9GbtLtmSrw==", "width": 1280, "ext": "webm", "vcodec": "vp9", "acodec": "none", "vbr": 85.731, "downloader_options": {"http_chunk_size": 10485760}, "container": "webm_dash", "format": "247 - 1280x720 (720p)", "protocol": "https", "http_headers": {"User-Agent": "Mozilla/5.0 (Windows NT 10.0; Win64; x64) AppleWebKit/537.36 (KHTML, like Gecko) Chrome/71.0.3578.1 Safari/537.36", "Accept-Charset": "ISO-8859-1,utf-8;q=0.7,*;q=0.7", "Accept": "text/html,application/xhtml+xml,application/xml;q=0.9,*/*;q=0.8", "Accept-Encoding": "gzip, deflate", "Accept-Language": "en-us,en;q=0.5"}}, {"asr": null, "filesize": 1821184, "format_id": "137", "format_note": "1080p", "fps": 30, "height": 1080, "quality": 5, "tbr": 72.137, "url": "https://r5---sn-a5msen7z.googlevideo.com/videoplayback?expire=1639283806&ei=_ie1YYENgrK7Aq-ls6AM&ip=66.214.92.208&id=o-ANL3vidtLiUQAAqrSW1Dtde0iaKhMlbpSAQnAyhv6V5m&itag=137&aitags=133%2C134%2C135%2C136%2C137%2C160%2C242%2C243%2C244%2C247%2C248%2C278&source=youtube&requiressl=yes&mh=AH&mm=31%2C29&mn=sn-a5msen7z%2Csn-a5meknzs&ms=au%2Crdu&mv=m&mvi=5&pl=20&ctier=A&pfa=5&initcwndbps=2172500&hightc=yes&vprv=1&mime=video%2Fmp4&ns=t2F5qZ-d7t3LU6Cz0gIBCo4G&gir=yes&clen=1821184&dur=201.968&lmt=1541906700521722&mt=1639261729&fvip=5&keepalive=yes&fexp=24001373%2C24007246&c=WEB&txp=5432432&n=YUPjBKJQ2Sav8E&sparams=expire%2Cei%2Cip%2Cid%2Caitags%2Csource%2Crequiressl%2Cctier%2Cpfa%2Chightc%2Cvprv%2Cmime%2Cns%2Cgir%2Cclen%2Cdur%2Clmt&lsparams=mh%2Cmm%2Cmn%2Cms%2Cmv%2Cmvi%2Cpl%2Cinitcwndbps&lsig=AG3C_xAwRAIgLDD4r6fAQOxn65w5Y8LpZPVc9d1lg5Ax8udYlp8GvOQCICXhyMe4cHNhlaEEgYGerZi5WcYKPs0mo8S5S4oNls-v&sig=AOq0QJ8wRQIhAKx8LV-VOQWgV7nbo3oQH7zGUP0FDm8LH331tAfQDqtEAiAx4EozVaXP0deUY6DeduDKydhnWdwRCeBjYojeDnV1Hw==", "width": 1920, "ext": "mp4", "vcodec": "avc1.640028", "acodec": "none", "vbr": 72.137, "downloader_options": {"http_chunk_size": 10485760}, "container": "mp4_dash", "format": "137 - 1920x1080 (1080p)", "protocol": "https", "http_headers": {"User-Agent": "Mozilla/5.0 (Windows NT 10.0; Win64; x64) AppleWebKit/537.36 (KHTML, like Gecko) Chrome/71.0.3578.1 Safari/537.36", "Accept-Charset": "ISO-8859-1,utf-8;q=0.7,*;q=0.7", "Accept": "text/html,application/xhtml+xml,application/xml;q=0.9,*/*;q=0.8", "Accept-Encoding": "gzip, deflate", "Accept-Language": "en-us,en;q=0.5"}}, {"asr": null, "filesize": 3493616, "format_id": "248", "format_note": "1080p", "fps": 30, "height": 1080, "quality": 5, "tbr": 138.382, "url": "https://r5---sn-a5msen7z.googlevideo.com/videoplayback?expire=1639283806&ei=_ie1YYENgrK7Aq-ls6AM&ip=66.214.92.208&id=o-ANL3vidtLiUQAAqrSW1Dtde0iaKhMlbpSAQnAyhv6V5m&itag=248&aitags=133%2C134%2C135%2C136%2C137%2C160%2C242%2C243%2C244%2C247%2C248%2C278&source=youtube&requiressl=yes&mh=AH&mm=31%2C29&mn=sn-a5msen7z%2Csn-a5meknzs&ms=au%2Crdu&mv=m&mvi=5&pl=20&ctier=A&pfa=5&initcwndbps=2172500&hightc=yes&vprv=1&mime=video%2Fwebm&ns=t2F5qZ-d7t3LU6Cz0gIBCo4G&gir=yes&clen=3493616&dur=201.968&lmt=1541907047761631&mt=1639261729&fvip=5&keepalive=yes&fexp=24001373%2C24007246&c=WEB&txp=5432432&n=YUPjBKJQ2Sav8E&sparams=expire%2Cei%2Cip%2Cid%2Caitags%2Csource%2Crequiressl%2Cctier%2Cpfa%2Chightc%2Cvprv%2Cmime%2Cns%2Cgir%2Cclen%2Cdur%2Clmt&lsparams=mh%2Cmm%2Cmn%2Cms%2Cmv%2Cmvi%2Cpl%2Cinitcwndbps&lsig=AG3C_xAwRAIgZ6BT6EtkZZoH1Twu34ZMjqgiOXeJXGXftUNoTRqqq5UCIDRS1LQOBVheHhcdzFVKsdn0N8boSyE2Y_fIYyrmzPVt&sig=AOq0QJ8wRgIhAOj1GkU8Z8eL8UZoZ4jLYiDCyqF-vRZifsm5PQXxSh-zAiEA9BOkAdbECFsXBjqd6oI7JL7k-Pc7zY9xMe4PHWUALJw=", "width": 1920, "ext": "webm", "vcodec": "vp9", "acodec": "none", "vbr": 138.382, "downloader_options": {"http_chunk_size": 10485760}, "container": "webm_dash", "format": "248 - 1920x1080 (1080p)", "protocol": "https", "http_headers": {"User-Agent": "Mozilla/5.0 (Windows NT 10.0; Win64; x64) AppleWebKit/537.36 (KHTML, like Gecko) Chrome/71.0.3578.1 Safari/537.36", "Accept-Charset": "ISO-8859-1,utf-8;q=0.7,*;q=0.7", "Accept": "text/html,application/xhtml+xml,application/xml;q=0.9,*/*;q=0.8", "Accept-Encoding": "gzip, deflate", "Accept-Language": "en-us,en;q=0.5"}}, {"asr": 44100, "filesize": 4283426, "format_id": "18", "format_note": "360p", "fps": 30, "height": 360, "quality": 2, "tbr": 169.59, "url": "https://r5---sn-a5msen7z.googlevideo.com/videoplayback?expire=1639283806&ei=_ie1YYENgrK7Aq-ls6AM&ip=66.214.92.208&id=o-ANL3vidtLiUQAAqrSW1Dtde0iaKhMlbpSAQnAyhv6V5m&itag=18&source=youtube&requiressl=yes&mh=AH&mm=31%2C29&mn=sn-a5msen7z%2Csn-a5meknzs&ms=au%2Crdu&mv=m&mvi=5&pl=20&ctier=A&pfa=5&initcwndbps=2172500&hightc=yes&vprv=1&mime=video%2Fmp4&ns=1QJV-NDheJyLg7HC_vSgpVsG&gir=yes&clen=4283426&ratebypass=yes&dur=202.060&lmt=1541907858998561&mt=1639261729&fvip=5&fexp=24001373%2C24007246&c=WEB&txp=5431432&n=KwKMHZkyO_Snt4&sparams=expire%2Cei%2Cip%2Cid%2Citag%2Csource%2Crequiressl%2Cctier%2Cpfa%2Chightc%2Cvprv%2Cmime%2Cns%2Cgir%2Cclen%2Cratebypass%2Cdur%2Clmt&lsparams=mh%2Cmm%2Cmn%2Cms%2Cmv%2Cmvi%2Cpl%2Cinitcwndbps&lsig=AG3C_xAwRAIgYnlZCyTteuEobcWv8Gn3gYKRiQGDybNoqTF9SxiX_iMCIFDwK1QEzGwYRINJWJHp0Hh-TxS1uNgnpH1qwJVeCGcy&sig=AOq0QJ8wRgIhAIe37hRUXAhQKINWR39oHkWtJkE9107ZBdwuKvfcjCxUAiEAylhqLjM_i2FaENC7k1Pi-IUxg88FcTe1a3QGAdcGtNQ=", "width": 640, "ext": "mp4", "vcodec": "avc1.42001E", "acodec": "mp4a.40.2", "format": "18 - 640x360 (360p)", "protocol": "https", "http_headers": {"User-Agent": "Mozilla/5.0 (Windows NT 10.0; Win64; x64) AppleWebKit/537.36 (KHTML, like Gecko) Chrome/71.0.3578.1 Safari/537.36", "Accept-Charset": "ISO-8859-1,utf-8;q=0.7,*;q=0.7", "Accept": "text/html,application/xhtml+xml,application/xml;q=0.9,*/*;q=0.8", "Accept-Encoding": "gzip, deflate", "Accept-Language": "en-us,en;q=0.5"}}], "thumbnails": [{"height": 94, "url": "https://i.ytimg.com/vi/JvDnmTdjg7E/hqdefault.jpg?sqp=-oaymwEbCKgBEF5IVfKriqkDDggBFQAAiEIYAXABwAEG&rs=AOn4CLAL8iU9Ne6KNC22PbXl0g5xr0UXog", "width": 168, "resolution": "168x94", "id": "0"}, {"height": 110, "url": "https://i.ytimg.com/vi/JvDnmTdjg7E/hqdefault.jpg?sqp=-oaymwEbCMQBEG5IVfKriqkDDggBFQAAiEIYAXABwAEG&rs=AOn4CLDwmT5cNZ1mgvTGXmTm7zAS2ZbF4Q", "width": 196, "resolution": "196x110", "id": "1"}, {"height": 138, "url": "https://i.ytimg.com/vi/JvDnmTdjg7E/hqdefault.jpg?sqp=-oaymwEcCPYBEIoBSFXyq4qpAw4IARUAAIhCGAFwAcABBg==&rs=AOn4CLDKWe5fhRJwdqaOk0QOGy-xYLA-Hw", "width": 246, "resolution": "246x138", "id": "2"}, {"height": 188, "url": "https://i.ytimg.com/vi/JvDnmTdjg7E/hqdefault.jpg?sqp=-oaymwEcCNACELwBSFXyq4qpAw4IARUAAIhCGAFwAcABBg==&rs=AOn4CLDUyiOFvH0BWUNWsw_p0tPxCU2wPw", "width": 336, "resolution": "336x188", "id": "3"}, {"height": 1080, "url": "https://i.ytimg.com/vi_webp/JvDnmTdjg7E/maxresdefault.webp", "width": 1920, "resolution": "1920x1080", "id": "4"}], "description": "\ucc38\uae68\uc640 \uc19c\uc0ac\ud0d5(Chamsom) - \uc774\uc990\uaed8(Forget you)\nof EP [\uc18d\ub9c8\uc74c(At Bottom)]\n* English & Chinese Subtitles are available. Click CC!\n\n\u25b6 iTunes\uff5chttps://itun.es/us/qMiBL\n\u25b6 Buy CD\uff5chttps://goo.gl/QthnJ8\n\n\nFor More Information about \ucc38\uae68\uc640 \uc19c\uc0ac\ud0d5 Chamsom\nhttps://instagram.com/real_chamsom\nhttps://www.facebook.com/chamsom.music\nhttps://twitter.com/cham_som\n\nFor More Information about \ud30c\uc2a4\ud154\ubba4\uc9c1 Pastel Music\nhttp://pastelcompany.com\nhttp://twitter.com/pastelmusiclife\nhttp://www.facebook.com/pastelmusic\nhttp://instagram.com/pastelmusic_\n\nAll rights reserved with Pastel Music.", "upload_date": "20160924", "uploader": "PASTEL TV", "uploader_id": "pastelmusic", "uploader_url": "http://www.youtube.com/user/pastelmusic", "channel_id": "UCkwrnbqSrID4CqlCmttlauw", "channel_url": "https://www.youtube.com/channel/UCkwrnbqSrID4CqlCmttlauw", "duration": 202, "view_count": 112053, "average_rating": 4.9395971, "age_limit": 0, "webpage_url": "https://www.youtube.com/watch?v=JvDnmTdjg7E", "categories": ["Music"], "tags": ["\ucc38\uae68\uc640\uc19c\uc0ac\ud0d5", "\ucc38\uc19c", "Chamsom", "\uc774\uc990\uaed8", "\uc18d\ub9c8\uc74c", "\ud30c\uc2a4\ud154\ubba4\uc9c1", "Pastel Music", "K-pop", "#Kpop", "K-Indie", "forget you"], "is_live": null, "subtitles": {"zh-Hans": [{"ext": "srv1", "url": "https://www.youtube.com/api/timedtext?v=JvDnmTdjg7E&asr_langs=de%2Cen%2Ces%2Cfr%2Cid%2Cit%2Cja%2Cko%2Cnl%2Cpt%2Cru%2Ctr%2Cvi&caps=asr&exp=xftt%2Cxctw&xoaf=5&hl=en&ip=0.0.0.0&ipbits=0&expire=1639287406&sparams=ip%2Cipbits%2Cexpire%2Cv%2Casr_langs%2Ccaps%2Cexp%2Cxoaf&signature=0B9EB92F04A0E2819F88C331D6C955DACC75D8E8.EA6BADEFCFD355405A16B2E18D7CC5A2363D03AA&key=yt8&lang=zh-Hans&fmt=srv1"}, {"ext": "srv2", "url": "https://www.youtube.com/api/timedtext?v=JvDnmTdjg7E&asr_langs=de%2Cen%2Ces%2Cfr%2Cid%2Cit%2Cja%2Cko%2Cnl%2Cpt%2Cru%2Ctr%2Cvi&caps=asr&exp=xftt%2Cxctw&xoaf=5&hl=en&ip=0.0.0.0&ipbits=0&expire=1639287406&sparams=ip%2Cipbits%2Cexpire%2Cv%2Casr_langs%2Ccaps%2Cexp%2Cxoaf&signature=0B9EB92F04A0E2819F88C331D6C955DACC75D8E8.EA6BADEFCFD355405A16B2E18D7CC5A2363D03AA&key=yt8&lang=zh-Hans&fmt=srv2"}, {"ext": "srv3", "url": "https://www.youtube.com/api/timedtext?v=JvDnmTdjg7E&asr_langs=de%2Cen%2Ces%2Cfr%2Cid%2Cit%2Cja%2Cko%2Cnl%2Cpt%2Cru%2Ctr%2Cvi&caps=asr&exp=xftt%2Cxctw&xoaf=5&hl=en&ip=0.0.0.0&ipbits=0&expire=1639287406&sparams=ip%2Cipbits%2Cexpire%2Cv%2Casr_langs%2Ccaps%2Cexp%2Cxoaf&signature=0B9EB92F04A0E2819F88C331D6C955DACC75D8E8.EA6BADEFCFD355405A16B2E18D7CC5A2363D03AA&key=yt8&lang=zh-Hans&fmt=srv3"}, {"ext": "ttml", "url": "https://www.youtube.com/api/timedtext?v=JvDnmTdjg7E&asr_langs=de%2Cen%2Ces%2Cfr%2Cid%2Cit%2Cja%2Cko%2Cnl%2Cpt%2Cru%2Ctr%2Cvi&caps=asr&exp=xftt%2Cxctw&xoaf=5&hl=en&ip=0.0.0.0&ipbits=0&expire=1639287406&sparams=ip%2Cipbits%2Cexpire%2Cv%2Casr_langs%2Ccaps%2Cexp%2Cxoaf&signature=0B9EB92F04A0E2819F88C331D6C955DACC75D8E8.EA6BADEFCFD355405A16B2E18D7CC5A2363D03AA&key=yt8&lang=zh-Hans&fmt=ttml"}, {"ext": "vtt", "url": "https://www.youtube.com/api/timedtext?v=JvDnmTdjg7E&asr_langs=de%2Cen%2Ces%2Cfr%2Cid%2Cit%2Cja%2Cko%2Cnl%2Cpt%2Cru%2Ctr%2Cvi&caps=asr&exp=xftt%2Cxctw&xoaf=5&hl=en&ip=0.0.0.0&ipbits=0&expire=1639287406&sparams=ip%2Cipbits%2Cexpire%2Cv%2Casr_langs%2Ccaps%2Cexp%2Cxoaf&signature=0B9EB92F04A0E2819F88C331D6C955DACC75D8E8.EA6BADEFCFD355405A16B2E18D7CC5A2363D03AA&key=yt8&lang=zh-Hans&fmt=vtt"}], "en": [{"ext": "srv1", "url": "https://www.youtube.com/api/timedtext?v=JvDnmTdjg7E&asr_langs=de%2Cen%2Ces%2Cfr%2Cid%2Cit%2Cja%2Cko%2Cnl%2Cpt%2Cru%2Ctr%2Cvi&caps=asr&exp=xftt%2Cxctw&xoaf=5&hl=en&ip=0.0.0.0&ipbits=0&expire=1639287406&sparams=ip%2Cipbits%2Cexpire%2Cv%2Casr_langs%2Ccaps%2Cexp%2Cxoaf&signature=0B9EB92F04A0E2819F88C331D6C955DACC75D8E8.EA6BADEFCFD355405A16B2E18D7CC5A2363D03AA&key=yt8&lang=en&fmt=srv1"}, {"ext": "srv2", "url": "https://www.youtube.com/api/timedtext?v=JvDnmTdjg7E&asr_langs=de%2Cen%2Ces%2Cfr%2Cid%2Cit%2Cja%2Cko%2Cnl%2Cpt%2Cru%2Ctr%2Cvi&caps=asr&exp=xftt%2Cxctw&xoaf=5&hl=en&ip=0.0.0.0&ipbits=0&expire=1639287406&sparams=ip%2Cipbits%2Cexpire%2Cv%2Casr_langs%2Ccaps%2Cexp%2Cxoaf&signature=0B9EB92F04A0E2819F88C331D6C955DACC75D8E8.EA6BADEFCFD355405A16B2E18D7CC5A2363D03AA&key=yt8&lang=en&fmt=srv2"}, {"ext": "srv3", "url": "https://www.youtube.com/api/timedtext?v=JvDnmTdjg7E&asr_langs=de%2Cen%2Ces%2Cfr%2Cid%2Cit%2Cja%2Cko%2Cnl%2Cpt%2Cru%2Ctr%2Cvi&caps=asr&exp=xftt%2Cxctw&xoaf=5&hl=en&ip=0.0.0.0&ipbits=0&expire=1639287406&sparams=ip%2Cipbits%2Cexpire%2Cv%2Casr_langs%2Ccaps%2Cexp%2Cxoaf&signature=0B9EB92F04A0E2819F88C331D6C955DACC75D8E8.EA6BADEFCFD355405A16B2E18D7CC5A2363D03AA&key=yt8&lang=en&fmt=srv3"}, {"ext": "ttml", "url": "https://www.youtube.com/api/timedtext?v=JvDnmTdjg7E&asr_langs=de%2Cen%2Ces%2Cfr%2Cid%2Cit%2Cja%2Cko%2Cnl%2Cpt%2Cru%2Ctr%2Cvi&caps=asr&exp=xftt%2Cxctw&xoaf=5&hl=en&ip=0.0.0.0&ipbits=0&expire=1639287406&sparams=ip%2Cipbits%2Cexpire%2Cv%2Casr_langs%2Ccaps%2Cexp%2Cxoaf&signature=0B9EB92F04A0E2819F88C331D6C955DACC75D8E8.EA6BADEFCFD355405A16B2E18D7CC5A2363D03AA&key=yt8&lang=en&fmt=ttml"}, {"ext": "vtt", "url": "https://www.youtube.com/api/timedtext?v=JvDnmTdjg7E&asr_langs=de%2Cen%2Ces%2Cfr%2Cid%2Cit%2Cja%2Cko%2Cnl%2Cpt%2Cru%2Ctr%2Cvi&caps=asr&exp=xftt%2Cxctw&xoaf=5&hl=en&ip=0.0.0.0&ipbits=0&expire=1639287406&sparams=ip%2Cipbits%2Cexpire%2Cv%2Casr_langs%2Ccaps%2Cexp%2Cxoaf&signature=0B9EB92F04A0E2819F88C331D6C955DACC75D8E8.EA6BADEFCFD355405A16B2E18D7CC5A2363D03AA&key=yt8&lang=en&fmt=vtt"}]}, "like_count": 1174, "channel": "PASTEL TV", "track": "\uc774\uc990\uaed8", "artist": "\ucc38\uae68\uc640 \uc19c\uc0ac\ud0d5", "creator": "\ucc38\uae68\uc640 \uc19c\uc0ac\ud0d5", "alt_title": "\uc774\uc990\uaed8", "extractor": "youtube", "webpage_url_basename": "JvDnmTdjg7E", "extractor_key": "Youtube", "n_entries": 101, "playlist": "WONDY", "playlist_id": "PLnKNmWNuQnyxWOcGJhaxJIQZnYiBtHcs2", "playlist_title": "WONDY", "playlist_uploader": "xG4mx", "playlist_uploader_id": "UCbxis4CTnlq-N44HUVjq-jw", "playlist_index": 1, "thumbnail": "https://i.ytimg.com/vi_webp/JvDnmTdjg7E/maxresdefault.webp", "display_id": "JvDnmTdjg7E", "format": "248 - 1920x1080 (1080p)+251 - audio only (tiny)", "format_id": "248+251", "width": 1920, "height": 1080, "resolution": null, "fps": 30, "vcodec": "vp9", "vbr": 138.382, "stretched_ratio": null, "acodec": "opus", "abr": 139.463, "ext": "webm", "fulltitle": "[Official Audio] \ucc38\uae68\uc640 \uc19c\uc0ac\ud0d5(Chamsom) - \uc774\uc990\uaed8(Forget you)", "_filename": "/Users/ehernand/Youtube-to-Spotify-Archiver/G4mx/WONDY/001_JvDnmTdjg7E_[Official Audio] \ucc38\uae68\uc640 \uc19c\uc0ac\ud0d5(Chamsom) - \uc774\uc990\uaed8(Forget you).webm"}